cython_blas/__init__.py
cython_blas/_blis.pxd
cython_blas/_cblas.pxd
cython_blas/_cyutility.abi3.so
cython_blas/blis.abi3.so
cython_blas/blis.pxd
cython_blas/blis.pyx
cython_blas/meson.build
cython_blas/openblas.abi3.so
cython_blas/openblas.pxd
cython_blas/openblas.pyx
cython_blas/optimize.py
cython_blas/tests/__init__.py
cython_blas/tests/test_blis.py
cython_blas/tests/test_openblas.py
cython_blas/tests/test_optimize.py
cython_blas/tests/utils.py
cython_blas.libs/libgcc_s-0cd532bd-c8f934f9.so.1
cython_blas.libs/libgfortran-2c33b284-17a27ac2.so.5.0.0
cython_blas.libs/libgomp-8949ffbe.so.1.0.0
cython_blas.libs/libquadmath-bb76a5fc-feb0f212.so.0.0.0
cython_blas.libs/libscipy_openblas64_-57b9cff5.so
cython_blas-0.1.1.dist-info/METADATA
cython_blas-0.1.1.dist-info/WHEEL
cython_blas-0.1.1.dist-info/RECORD
cython_blas-0.1.1.dist-info/licenses/LICENSE.txt
