Metadata-Version: 2.4
Name: cython-blas
Version: 0.1.1
Summary: Wrappers around OpenBLAS and BLIS.
Author-Email: Josh Ayers <josh@ayers.pw>
License-Expression: MIT
License-File: LICENSE.txt
Classifier: Development Status :: 3 - Alpha
Classifier: Programming Language :: C
Classifier: Programming Language :: Python
Classifier: Programming Language :: Python :: 3.11
Classifier: Programming Language :: Python :: 3.12
Classifier: Programming Language :: Python :: 3.13
Classifier: Programming Language :: Python :: 3 :: Only
Classifier: Programming Language :: Python :: Implementation :: CPython
Classifier: Natural Language :: English
Classifier: Intended Audience :: Developers
Classifier: Intended Audience :: Science/Research
Classifier: Topic :: Scientific/Engineering
Classifier: Topic :: Software Development
Classifier: Operating System :: Microsoft :: Windows
Classifier: Operating System :: POSIX
Project-URL: Repository, https://github.com/joshayers/cython-blas/
Requires-Python: >=3.11
Requires-Dist: numpy>=2.0
Provides-Extra: docs
Requires-Dist: sphinx>=8.1; extra == "docs"
Requires-Dist: sphinx-rtd-theme; extra == "docs"
Provides-Extra: test
Requires-Dist: pytest; extra == "test"
Provides-Extra: lint
Requires-Dist: deptry; extra == "lint"
Requires-Dist: ruff; extra == "lint"
Requires-Dist: isort; extra == "lint"
Requires-Dist: cython-lint; extra == "lint"
Provides-Extra: dev
Requires-Dist: sphinx>=8.1; extra == "dev"
Requires-Dist: sphinx-rtd-theme; extra == "dev"
Requires-Dist: pytest; extra == "dev"
Requires-Dist: deptry; extra == "dev"
Requires-Dist: ruff; extra == "dev"
Requires-Dist: isort; extra == "dev"
Requires-Dist: cython-lint; extra == "dev"
Requires-Dist: scipy-openblas64==0.3.30.0.1; extra == "dev"
Requires-Dist: cython>=3.1.0; extra == "dev"
Requires-Dist: meson-python>=0.17.0; extra == "dev"
Requires-Dist: ninja>=1.11; extra == "dev"
Requires-Dist: build; extra == "dev"
Requires-Dist: spin; extra == "dev"
Requires-Dist: click; extra == "dev"
